simple_robomaster/__init__.py
simple_robomaster/simple_robot.py
simple_robomaster-0.1.1.dist-info/LICENSE
simple_robomaster-0.1.1.dist-info/METADATA
simple_robomaster-0.1.1.dist-info/WHEEL
simple_robomaster-0.1.1.dist-info/top_level.txt
simple_robomaster-0.1.1.dist-info/RECORD
