Metadata-Version: 2.1
Name: simple-robomaster
Version: 0.1.1
Summary: Simple Wrapper for Robot
Home-page: https://github.com/levon-gevorgyan/simple_robomaster
Author: Levon Gevorgyan
Author-email: levongevdav@gmail.com
License: UNKNOWN
Project-URL: Bug Tracker, https://github.com/levon-gevorgyan/simple_robomaster/issues
Platform: UNKNOWN
Classifier: Programming Language :: Python :: 3
Classifier: License :: OSI Approved :: MIT License
Classifier: Operating System :: OS Independent
Requires-Python: >=3.6
License-File: LICENSE
Requires-Dist: robomaster (>=0.1.1.65)
